dynalock/__init__.py
dynalock/dynalock.py
dynalock/exceptions.py
dynalock-0.3.0.dist-info/AUTHORS.rst
dynalock-0.3.0.dist-info/LICENSE
dynalock-0.3.0.dist-info/METADATA
dynalock-0.3.0.dist-info/WHEEL
dynalock-0.3.0.dist-info/top_level.txt
dynalock-0.3.0.dist-info/RECORD
