Metadata-Version: 2.1
Name: dynalock
Version: 0.3.0
Summary: Distributed locking with DynamoDB
Home-page: https://github.com/skywalker427/dynalock
Author: Hamzah Bawah
Author-email: bhamza123@gmail.com
License: MIT license
Keywords: dynalock
Classifier: Development Status :: 2 - Pre-Alpha
Classifier: Intended Audience :: Developers
Classifier: License :: OSI Approved :: MIT License
Classifier: Natural Language :: English
Classifier: Programming Language :: Python :: 3
Classifier: Programming Language :: Python :: 3.6
Classifier: Programming Language :: Python :: 3.7
Classifier: Programming Language :: Python :: 3.8
Requires-Python: >=3.6
License-File: LICENSE
License-File: AUTHORS.rst
Requires-Dist: boto3 >=1.34.74
Requires-Dist: botocore >=1.34.74
